fg/__init__.py
fg-0.0.5.dist-info/licenses/LICENSE
fg-0.0.5.dist-info/METADATA
fg-0.0.5.dist-info/WHEEL
fg-0.0.5.dist-info/top_level.txt
fg-0.0.5.dist-info/RECORD
