Metadata-Version: 2.4
Name: fg
Version: 0.0.5
Summary: Elastic Search access
Home-page: https://github.com/t-c-w/fg
Author: Thor Whalen
License: apache-2.0
Platform: any
License-File: LICENSE
Dynamic: license-file
